minisom2onnx/__init__.py
minisom2onnx/minisom2onnx.py
minisom2onnx/version.py
minisom2onnx-0.1.0.dist-info/LICENSE
minisom2onnx-0.1.0.dist-info/METADATA
minisom2onnx-0.1.0.dist-info/WHEEL
minisom2onnx-0.1.0.dist-info/top_level.txt
minisom2onnx-0.1.0.dist-info/RECORD
