Metadata-Version: 2.1
Name: minisom2onnx
Version: 0.1.0
Summary: A library to convert MiniSom models to ONNX format
Home-page: https://github.com/chiragasourabh/minisom-onnx
Author: Chiragasourabh
Author-email: chiragasourabh@gmail.com
License: MIT
Keywords: minisom,onnx,som,machine learning,self organising maps
Classifier: Programming Language :: Python :: 3
Classifier: License :: OSI Approved :: MIT License
Classifier: Operating System :: OS Independent
Classifier: Intended Audience :: Developers
Requires-Python: >=3.8
License-File: LICENSE
Requires-Dist: numpy
Requires-Dist: onnx >=1.14.0
Requires-Dist: minisom >=2.3.0
